tensorflowjs/__init__.py
tensorflowjs/converters/__init__.py
tensorflowjs/converters/common.py
tensorflowjs/converters/converter
tensorflowjs/converters/converter.py
tensorflowjs/converters/fold_batch_norms.py
tensorflowjs/converters/fuse_depthwise_conv2d.py
tensorflowjs/converters/fuse_prelu.py
tensorflowjs/converters/graph_rewrite_util.py
tensorflowjs/converters/jax_conversion.py
tensorflowjs/converters/keras_h5_conversion.py
tensorflowjs/converters/keras_tfjs_loader.py
tensorflowjs/converters/normalize_bias_add.py
tensorflowjs/converters/tf_module_mapper.py
tensorflowjs/converters/tf_saved_model_conversion_v2.py
tensorflowjs/converters/wizard
tensorflowjs/converters/wizard.py
tensorflowjs/op_list/arithmetic.json
tensorflowjs/op_list/basic_math.json
tensorflowjs/op_list/control.json
tensorflowjs/op_list/convolution.json
tensorflowjs/op_list/creation.json
tensorflowjs/op_list/dynamic.json
tensorflowjs/op_list/evaluation.json
tensorflowjs/op_list/graph.json
tensorflowjs/op_list/hash_table.json
tensorflowjs/op_list/image.json
tensorflowjs/op_list/logical.json
tensorflowjs/op_list/matrices.json
tensorflowjs/op_list/normalization.json
tensorflowjs/op_list/ragged.json
tensorflowjs/op_list/reduction.json
tensorflowjs/op_list/slice_join.json
tensorflowjs/op_list/sparse.json
tensorflowjs/op_list/spectral.json
tensorflowjs/op_list/string.json
tensorflowjs/op_list/tfdf.json
tensorflowjs/op_list/transformation.json
tensorflowjs/quantization.py
tensorflowjs/read_weights.py
tensorflowjs/resource_loader.py
tensorflowjs/version.py
tensorflowjs/write_weights.py
tensorflowjs-4.21.0.dist-info/METADATA
tensorflowjs-4.21.0.dist-info/RECORD
tensorflowjs-4.21.0.dist-info/WHEEL
tensorflowjs-4.21.0.dist-info/entry_points.txt
