Metadata-Version: 2.1
Name: tensorflowjs
Author: Google LLC
Author-email: opensource@google.com
Home-page: https://js.tensorflow.org/
License: Apache 2.0
Classifier: Development Status :: 3 - Alpha
Classifier: Intended Audience :: Developers
Classifier: Intended Audience :: Education
Classifier: Intended Audience :: Science/Research
Classifier: License :: OSI Approved :: Apache Software License
Classifier: Programming Language :: JavaScript
Classifier: Programming Language :: Python :: 2
Classifier: Programming Language :: Python :: 3
Classifier: Topic :: Scientific/Engineering
Classifier: Topic :: Scientific/Engineering :: Mathematics
Classifier: Topic :: Scientific/Engineering :: Artificial Intelligence
Classifier: Topic :: Software Development
Classifier: Topic :: Software Development :: Libraries
Classifier: Topic :: Software Development :: Libraries :: Python Modules
Requires-Dist: flax>=0.7.2
Requires-Dist: importlib_resources>=5.9.0
Requires-Dist: jax>=0.4.13
Requires-Dist: jaxlib>=0.4.13
Requires-Dist: tensorflow>=2.13.0,<3
Requires-Dist: tf-keras>=2.13.0
Requires-Dist: tensorflow-decision-forests>=1.5.0
Requires-Dist: six>=1.16.0,<2
Requires-Dist: tensorflow-hub>=0.16.1
Requires-Dist: packaging~=23.1
Provides-Extra: PyInquirer
Requires-Dist: PyInquirer==1.0.3; extra == 'PyInquirer'
Provides-Extra: all
Requires-Dist: PyInquirer==1.0.3; extra == 'all'
Provides-Extra: wizard
Requires-Dist: PyInquirer==1.0.3; extra == 'wizard'
Version: 4.21.0
